metatree/__init__.py
metatree/io_handler.py
metatree/metatree.py
metatree/util.py
tests/__init__.py
tests/simple_http_server.py
tests/test_metatree.py
tests/test_util.py
metatreedb-0.2.3.dist-info/LICENSE
metatreedb-0.2.3.dist-info/METADATA
metatreedb-0.2.3.dist-info/WHEEL
metatreedb-0.2.3.dist-info/top_level.txt
metatreedb-0.2.3.dist-info/RECORD
