Metadata-Version: 2.1
Name: metatreedb
Version: 0.2.3
Summary: Metatree is a DBMS that uses the filesystem itself as a tree-structured database.
Home-page: https://github.com/oboki/metatreedb
Author: oboki
Author-email: oboki@kakao.com
License: UNKNOWN
Platform: UNKNOWN
Classifier: Programming Language :: Python :: 3
Classifier: License :: OSI Approved :: MIT License
Requires-Python: >=3.7
Requires-Dist: fsspec
Requires-Dist: hdfs
Requires-Dist: pyyaml
Requires-Dist: s3fs
Provides-Extra: dev
Requires-Dist: pytest; extra == "dev"
Requires-Dist: wheel; extra == "dev"
